deeplcmd/__init__.py
deeplcmd/deeplcmd.py
deeplcmd-0.1.4.dist-info/LICENSE
deeplcmd-0.1.4.dist-info/METADATA
deeplcmd-0.1.4.dist-info/WHEEL
deeplcmd-0.1.4.dist-info/entry_points.txt
deeplcmd-0.1.4.dist-info/top_level.txt
deeplcmd-0.1.4.dist-info/RECORD
