Metadata-Version: 2.1
Name: deeplcmd
Version: 0.1.4
Summary: DeepLCMD is a simple command line app for text and document translation with Deepl Translator API 
Home-page: https://github.com/ilya-smut/deeplcmd
Author: Ilya Smut
Author-email: ilya.smut.off.g@gmail.com
License: GPL-3.0 license
Project-URL: Source Code, https://github.com/ilya-smut/deeplcmd
License-File: LICENSE
Requires-Dist: Click
Requires-Dist: Deepl
